MySpinalProject/simWorkspace/Dut/rtl/Dut.v
// Generator : SpinalHDL v1.10.1    git head : 2527c7c6b0fb0f95e5e1a5722a0be732b364ce43
// Component : Dut
// Git hash  : efa66e4f8da67c842f46e524ba6fe565b73f5b0b

`timescale 1ns/1ps

module Dut (
  input  wire [7:0]    io_a,
  input  wire [7:0]    io_b,
  output wire [7:0]    io_result,
  input  wire          clk,
  input  wire          reset
);

  wire       [7:0]    carryAdder_1_io_result;

  CarryAdder carryAdder_1 (
    .io_a      (io_a[7:0]                  ), //i
    .io_b      (io_b[7:0]                  ), //i
    .io_result (carryAdder_1_io_result[7:0])  //o
  );
  assign io_result = carryAdder_1_io_result;

endmodule

module CarryAdder (
  input  wire [7:0]    io_a,
  input  wire [7:0]    io_b,
  output reg  [7:0]    io_result
);

  reg                 c_8;
  reg                 c_7;
  reg                 c_6;
  reg                 c_5;
  reg                 c_4;
  reg                 c_3;
  reg                 c_2;
  reg                 c_1;
  wire                c;
  wire                _zz_c_1;
  wire                _zz_c_1_1;
  wire                _zz_c_2;
  wire                _zz_c_2_1;
  wire                _zz_c_3;
  wire                _zz_c_3_1;
  wire                _zz_c_4;
  wire                _zz_c_4_1;
  wire                _zz_c_5;
  wire                _zz_c_5_1;
  wire                _zz_c_6;
  wire                _zz_c_6_1;
  wire                _zz_c_7;
  wire                _zz_c_7_1;
  wire                _zz_c_8;
  wire                _zz_c_8_1;

  always @(*) begin
    c_8 = c_7;
    c_8 = (((_zz_c_8 && _zz_c_8_1) || (_zz_c_8 && c_7)) || (_zz_c_8_1 && c_7));
  end

  always @(*) begin
    c_7 = c_6;
    c_7 = (((_zz_c_7 && _zz_c_7_1) || (_zz_c_7 && c_6)) || (_zz_c_7_1 && c_6));
  end

  always @(*) begin
    c_6 = c_5;
    c_6 = (((_zz_c_6 && _zz_c_6_1) || (_zz_c_6 && c_5)) || (_zz_c_6_1 && c_5));
  end

  always @(*) begin
    c_5 = c_4;
    c_5 = (((_zz_c_5 && _zz_c_5_1) || (_zz_c_5 && c_4)) || (_zz_c_5_1 && c_4));
  end

  always @(*) begin
    c_4 = c_3;
    c_4 = (((_zz_c_4 && _zz_c_4_1) || (_zz_c_4 && c_3)) || (_zz_c_4_1 && c_3));
  end

  always @(*) begin
    c_3 = c_2;
    c_3 = (((_zz_c_3 && _zz_c_3_1) || (_zz_c_3 && c_2)) || (_zz_c_3_1 && c_2));
  end

  always @(*) begin
    c_2 = c_1;
    c_2 = (((_zz_c_2 && _zz_c_2_1) || (_zz_c_2 && c_1)) || (_zz_c_2_1 && c_1));
  end

  always @(*) begin
    c_1 = c;
    c_1 = (((_zz_c_1 && _zz_c_1_1) || (_zz_c_1 && c)) || (_zz_c_1_1 && c));
  end

  assign c = 1'b0;
  assign _zz_c_1 = io_a[0];
  assign _zz_c_1_1 = io_b[0];
  always @(*) begin
    io_result[0] = ((_zz_c_1 ^ _zz_c_1_1) ^ c);
    io_result[1] = ((_zz_c_2 ^ _zz_c_2_1) ^ c_1);
    io_result[2] = ((_zz_c_3 ^ _zz_c_3_1) ^ c_2);
    io_result[3] = ((_zz_c_4 ^ _zz_c_4_1) ^ c_3);
    io_result[4] = ((_zz_c_5 ^ _zz_c_5_1) ^ c_4);
    io_result[5] = ((_zz_c_6 ^ _zz_c_6_1) ^ c_5);
    io_result[6] = ((_zz_c_7 ^ _zz_c_7_1) ^ c_6);
    io_result[7] = ((_zz_c_8 ^ _zz_c_8_1) ^ c_7);
  end

  assign _zz_c_2 = io_a[1];
  assign _zz_c_2_1 = io_b[1];
  assign _zz_c_3 = io_a[2];
  assign _zz_c_3_1 = io_b[2];
  assign _zz_c_4 = io_a[3];
  assign _zz_c_4_1 = io_b[3];
  assign _zz_c_5 = io_a[4];
  assign _zz_c_5_1 = io_b[4];
  assign _zz_c_6 = io_a[5];
  assign _zz_c_6_1 = io_b[5];
  assign _zz_c_7 = io_a[6];
  assign _zz_c_7_1 = io_b[6];
  assign _zz_c_8 = io_a[7];
  assign _zz_c_8_1 = io_b[7];

endmodule

MySpinalProject/simWorkspace/Dut/test/wave.vcd
$version Generated by VerilatedVcd $end
$date Tue 27 Aug 2024 01:01:54 PM CEST $end
$timescale 1s $end

 $scope module TOP $end
  $var wire  1 . clk $end
  $var wire  8 + io_a [7:0] $end
  $var wire  8 , io_b [7:0] $end
  $var wire  8 - io_result [7:0] $end
  $var wire  1 / reset $end
  $scope module Dut $end
   $var wire  8 # carryAdder_1_io_result [7:0] $end
   $var wire  1 . clk $end
   $var wire  8 + io_a [7:0] $end
   $var wire  8 , io_b [7:0] $end
   $var wire  8 - io_result [7:0] $end
   $var wire  1 / reset $end
   $scope module carryAdder_1 $end
    $var wire  1 1 c $end
    $var wire  1 * c_1 $end
    $var wire  1 ) c_2 $end
    $var wire  1 ( c_3 $end
    $var wire  1 ' c_4 $end
    $var wire  1 & c_5 $end
    $var wire  1 % c_6 $end
    $var wire  1 $ c_7 $end
    $var wire  1 0 c_8 $end
    $var wire  8 + io_a [7:0] $end
    $var wire  8 , io_b [7:0] $end
    $var wire  8 # io_result [7:0] $end
   $upscope $end
  $upscope $end
 $upscope $end
$enddefinitions $end


#0
b10100101 #
0$
0%
1&
0'
0(
0)
0*
b00010101 +
b10010000 ,
b10100101 -
1.
1/
00
01
#1
b00000000 #
1$
1%
1'
1(
1)
b10011010 +
b01100110 ,
b00000000 -
10
#2
b10111011 #
0$
0%
0&
0'
0(
0)
b10001011 +
b00110000 ,
b10111011 -
00
#3
b00000111 #
1$
1%
1&
1'
b01101110 +
b10011001 ,
b00000111 -
10
#4
b11100110 #
0$
0%
b10011100 +
b01001010 ,
b11100110 -
00
#5
b11101111 #
1%
0'
b00111011 +
b10110100 ,
b11101111 -
#6
b10111101 #
0%
0&
b10010101 +
b00101000 ,
b10111101 -
#7
b00011110 #
1$
1%
1)
1*
b00101011 +
b11110011 ,
b00011110 -
10
#8
b10000011 #
1&
0)
0*
b10010011 +
b11110000 ,
b10000011 -
#9
b01101010 #
0$
0%
1'
1(
1*
b00001101 +
b01011101 ,
b01101010 -
00
#10
b11100011 #
0(
0*
b01011001 +
b10001010 ,
b11100011 -
#11
b00101110 #
0&
0'
b00000110 +
b00101000 ,
b00101110 -
#12
b00110101 #
1$
1'
b01001000 +
b11101101 ,
b00110101 -
10
#13
b01000110 #
0$
0'
b00000100 +
b01000010 ,
b01000110 -
00
#14
b11101111 #
1&
b00010011 +
b11011100 ,
b11101111 -
#15
b10001101 #
1$
1%
b00111101 +
b01010000 ,
b10001101 -
#16
b01100010 #
1'
1(
1)
1*
b11111011 +
b01100111 ,
b01100010 -
10
#17
b01000111 #
0(
0)
0*
b01111000 +
b11001111 ,
b01000111 -
#18
b01011110 #
0$
0%
0&
0'
b10001100 +
b11010010 ,
b01011110 -
#19
b00000111 #
1$
b01000010 +
b11000101 ,
b00000111 -
#20
b10111111 #
b11001010 +
b11110101 ,
b10111111 -
#21
b01111011 #
0$
b11100011 +
b10011000 ,
b01111011 -
#22
b11100011 #
1&
1'
b11001000 +
b00011011 ,
b11100011 -
00
#23
b00011101 #
1$
0&
0'
b11010000 +
b01001101 ,
b00011101 -
10
#24
1%
1&
1'
1(
1)
b10111111 +
b01011110 ,
#25
b10000000 #
1*
b00001011 +
b01110101 ,
b10000000 -
00
#26
b11110001 #
0$
0%
0&
0(
0)
0*
b11001001 +
b00101000 ,
b11110001 -
#27
b00001011 #
1$
1%
0'
1(
b00100110 +
b11100101 ,
b00001011 -
10
#28
b01011011 #
1&
1'
b11011101 +
b01111110 ,
b01011011 -
#29
b00011111 #
0%
0&
0'
0(
b11010100 +
b01001011 ,
b00011111 -
#30
b10100001 #
1%
1&
1'
1(
1)
b01111111 +
b00100010 ,
b10100001 -
00
#31
b00100010 #
1*
b00110011 +
b11101111 ,
b00100010 -
10
#32
b01110110 #
0$
0%
0&
0(
0)
b00001101 +
b01101001 ,
b01110110 -
00
#33
b11110001 #
1&
1(
0*
b10010100 +
b01011101 ,
b11110001 -
#34
b10101001 #
1$
0&
0'
0(
b11001001 +
b11100000 ,
b10101001 -
10
#35
b01110000 #
0$
1'
1(
1)
1*
b00000101 +
b01101011 ,
b01110000 -
00
#36
b11011001 #
1$
1%
1&
0*
b01111110 +
b01011011 ,
b11011001 -
#37
b00101001 #
0$
0%
0'
b10010011 +
b10010110 ,
b00101001 -
10
#38
b10011101 #
1$
1%
0&
0(
0)
b00111000 +
b01100101 ,
b10011101 -
00
#39
b00101110 #
0%
1*
b11000101 +
b01101001 ,
b00101110 -
10
#40
b10110010 #
0$
1'
1(
0*
b10000100 +
b00101110 ,
b10110010 -
00
#41
b01101010 #
0'
0(
b11001010 +
b10100000 ,
b01101010 -
10
#42
b10011010 #
1(
b10000110 +
b00010100 ,
b10011010 -
00
#43
b01011101 #
0(
b00000000 +
b01011101 ,
b01011101 -
#44
b01100111 #
b11100000 +
b10000111 ,
b01100111 -
10
#45
b00110111 #
1'
b10001110 +
b10101001 ,
b00110111 -
#46
b01001001 #
0'
1(
1)
b11000011 +
b10000110 ,
b01001001 -
#47
b10100101 #
1$
1%
1&
1'
b10110111 +
b11101110 ,
b10100101 -
#48
b01011000 #
0$
0%
0&
0'
1*
b01000001 +
b00010111 ,
b01011000 -
00
#49
b11011001 #
1%
0)
0*
b00100100 +
b10110101 ,
b11011001 -
#50
b01110101 #
1&
1'
0(
1)
b10111011 +
b10111010 ,
b01110101 -
10
#51
b11110100 #
1$
1(
b11110110 +
b11111110 ,
b11110100 -
#52
b11101000 #
0$
0%
0&
0'
1*
b11100001 +
b00000111 ,
b11101000 -
00
#53
b01110110 #
0(
0)
0*
b10000010 +
b11110100 ,
b01110110 -
10
#54
b10010110 #
1'
1*
b10001001 +
b00001101 ,
b10010110 -
00
#55
b01110001 #
1(
1)
0*
b01000011 +
b00101110 ,
b01110001 -
#56
b00010000 #
1$
1%
1*
b01101011 +
b10100101 ,
b00010000 -
10
#57
b11111000 #
0$
0%
0*
b11001010 +
b00101110 ,
b11111000 -
00
#58
b01101101 #
0'
0(
0)
b00100101 +
b01001000 ,
b01101101 -
#59
b00000111 #
1$
b01000111 +
b11000000 ,
b00000111 -
10
#60
b00001001 #
1%
1&
1'
1(
1)
b10111011 +
b01001110 ,
b00001001 -
#61
b01100001 #
0)
b11111100 +
b01100101 ,
b01100001 -
#62
b01100111 #
0(
b01101010 +
b11111101 ,
b01100111 -
#63
b01010011 #
0&
1(
b01101110 +
b11100101 ,
b01010011 -
#64
b00111001 #
0$
0%
0'
1)
b10000110 +
b10110011 ,
b00111001 -
#65
b10010100 #
1'
0(
1*
b10001001 +
b00001011 ,
b10010100 -
00
#66
b01000000 #
1%
1&
1(
0)
0*
b00101100 +
b00010100 ,
b01000000 -
#67
b11010000 #
0&
1)
1*
b00101001 +
b10100111 ,
b11010000 -
#68
b01001100 #
1$
0'
0(
0*
b11100010 +
b01101010 ,
b01001100 -
10
#69
b00010101 #
1&
1'
1(
b00111110 +
b11010111 ,
b00010101 -
#70
b11001111 #
0$
0&
0'
0(
0)
b00100101 +
b10101010 ,
b11001111 -
00
#71
b11110110 #
0%
1*
b10100001 +
b01010101 ,
b11110110 -
#72
b00101010 #
1$
1%
1&
1'
1(
0*
b00101100 +
b11111110 ,
b00101010 -
10
#73
b10111101 #
0%
0&
0'
0(
b11011001 +
b11100100 ,
b10111101 -
#74
b11001010 #
1%
1&
1'
1(
1)
1*
b11001011 +
b11111111 ,
b11001010 -
#75
b10000001 #
0)
0*
b01100101 +
b00011100 ,
b10000001 -
00
#76
b11100101 #
0$
0%
0(
1)
b01001010 +
b10011011 ,
b11100101 -
#77
b01111100 #
0&
1(
1*
b01001101 +
b00101111 ,
b01111100 -
#78
b00000011 #
1$
1%
1&
0)
0*
b10010111 +
b01101100 ,
b00000011 -
10
#79
b01001111 #
0$
0'
0(
b10011110 +
b10110001 ,
b01001111 -
#80
b10101110 #
1$
1(
1)
1*
b11110111 +
b10110111 ,
b10101110 -
#81
b00001001 #
0&
0(
0)
0*
b01101001 +
b10100000 ,
b00001001 -
#82
b00100100 #
1&
1)
b11110010 +
b00110010 ,
b00100100 -
#83
b00000110 #
0%
0&
0)
b11000000 +
b01000110 ,
b00000110 -
#84
b10100000 #
0$
1&
1'
1(
1)
1*
b10000101 +
b00011011 ,
b10100000 -
00
#85
b11100100 #
0'
0(
b00010001 +
b11010011 ,
b11100100 -
#86
b11100010 #
1'
0)
b11001001 +
b00011001 ,
b11100010 -
#87
b01110111 #
0&
0'
0*
b10110000 +
b11000111 ,
b01110111 -
10
#88
b11000101 #
1%
1&
1'
1(
1)
b10111111 +
b00000110 ,
b11000101 -
00
#89
b00100011 #
1$
0'
0(
0)
b10110001 +
b01110010 ,
b00100011 -
10
#90
b10001010 #
b10110010 +
b11011000 ,
b10001010 -
#91
b11000110 #
1'
1*
b01101001 +
b01011101 ,
b11000110 -
00
#92
b10010001 #
0&
0*
b01101000 +
b00101001 ,
b10010001 -
#93
b01100001 #
0$
0%
1&
1(
1)
b11011110 +
b10000011 ,
b01100001 -
10
#94
b00001010 #
1$
1%
0'
0(
0)
b10110000 +
b01011010 ,
b00001010 -
#95
b01101100 #
0$
0%
0&
1)
1*
b00001011 +
b01100001 ,
b01101100 -
00
#96
b00100101 #
1$
1%
1&
0*
b01110010 +
b10110011 ,
b00100101 -
10
#97
b11010100 #
0$
0%
0&
0)
b10000000 +
b01010100 ,
b11010100 -
00
#98
b00001101 #
1$
1%
1(
1)
b11100110 +
b00100111 ,
b00001101 -
10
#99
b11000000 #
0$
1&
1'
1*
b00100111 +
b10011001 ,
b11000000 -
00
